{"indicator":"16.1.3","target_id":"16.1","sdg_goal":"16","reporting_status":"complete","data_non_statistical":false,"graph_type":"line","indicator_sort_order":"16-01-03","indicator_name":"Proporcio\u0301n de la poblacio\u0301n que ha sufrido a) violencia fi\u0301sica, b) violencia psicolo\u0301gica y c) violencia sexual en los u\u0301ltimos 12 meses","graph_title":"Proporcio\u0301n de la poblacio\u0301n que ha sufrido a) violencia fi\u0301sica, b) violencia psicolo\u0301gica y c) violencia sexual en los u\u0301ltimos 12 meses"}